imagerie/__init__.py
imagerie/imagerie.py
imagerie/_lib/__init__.py
imagerie/_lib/_util.py
imagerie/_lib/six.py
imagerie/ndimage/__init__.py
imagerie/ndimage/_nd_image.py
imagerie/ndimage/_ni_label.py
imagerie/ndimage/_ni_support.py
imagerie/operations/__init__.py
imagerie/operations/distance.py
imagerie/operations/img.py
imagerie/operations/img_format.py
imagerie/operations/measurements.py
imagerie/operations/morphology.py
imagerie-0.0.11.dist-info/LICENSE
imagerie-0.0.11.dist-info/METADATA
imagerie-0.0.11.dist-info/WHEEL
imagerie-0.0.11.dist-info/top_level.txt
imagerie-0.0.11.dist-info/RECORD
